m365_user_manager/__init__.py
m365_user_manager/__main__.py
m365_user_manager/config/__init__.py
m365_user_manager/config/__pycache__/__init__.cpython-312.pyc
m365_user_manager/config/__pycache__/default_config.cpython-312.pyc
m365_user_manager/config/default_config.py
m365_user_manager/core/__init__.py
m365_user_manager/core/__pycache__/__init__.cpython-312.pyc
m365_user_manager/core/__pycache__/orchestrator.cpython-312.pyc
m365_user_manager/core/orchestrator.py
m365_user_manager/core/sync_orchestrator.py
m365_user_manager/exceptions/__init__.py
m365_user_manager/exceptions/__pycache__/__init__.cpython-312.pyc
m365_user_manager/exceptions/__pycache__/exceptions.cpython-312.pyc
m365_user_manager/exceptions/exceptions.py
m365_user_manager/main.py
m365_user_manager/managers/__init__.py
m365_user_manager/managers/__pycache__/__init__.cpython-312.pyc
m365_user_manager/managers/__pycache__/environment_manager.cpython-312.pyc
m365_user_manager/managers/__pycache__/password_manager.cpython-312.pyc
m365_user_manager/managers/__pycache__/token_manager.cpython-312.pyc
m365_user_manager/managers/__pycache__/user_manager.cpython-312.pyc
m365_user_manager/managers/cache_manager.py
m365_user_manager/managers/environment_manager.py
m365_user_manager/managers/membership_manager.py
m365_user_manager/managers/password_manager.py
m365_user_manager/managers/request_manager.py
m365_user_manager/managers/token_manager.py
m365_user_manager/managers/user_manager.py
m365_user_manager/use_create_user.py
m365_user_manager/utils/__init__.py
m365_user_manager/utils/__pycache__/__init__.cpython-312.pyc
m365_user_manager/utils/__pycache__/input_processor.cpython-312.pyc
m365_user_manager/utils/__pycache__/result_handler.cpython-312.pyc
m365_user_manager/utils/input_identifiers.py
m365_user_manager/utils/input_processor.py
m365_user_manager/utils/result_handler.py
m365_user_manager/utils/results/user_result.json
m365_user_manager-0.1.1rc14.dist-info/LICENSE
m365_user_manager-0.1.1rc14.dist-info/METADATA
m365_user_manager-0.1.1rc14.dist-info/WHEEL
m365_user_manager-0.1.1rc14.dist-info/RECORD
