Metadata-Version: 2.3
Name: m365-user-manager
Version: 0.1.1rc14
Summary: A package dedicated to creating new users in o365
License: MIT
Author: VinnyVanGogh
Author-email: 133192356+VinnyVanGogh@users.noreply.github.com
Requires-Python: >=3.11,<4.0
Classifier: License :: OSI Approved :: MIT License
Classifier: Programming Language :: Python :: 3
Classifier: Programming Language :: Python :: 3.11
Classifier: Programming Language :: Python :: 3.12
Classifier: Programming Language :: Python :: 3.13
Requires-Dist: aiohappyeyeballs (==2.4.4)
Requires-Dist: aiohttp (==3.11.11)
Requires-Dist: aiosignal (==1.3.2)
Requires-Dist: attrs (==25.1.0)
Requires-Dist: certifi (==2024.12.14)
Requires-Dist: charset-normalizer (==3.4.1)
Requires-Dist: colorlog (==6.9.0)
Requires-Dist: cw-rpa (==0.1.0b10)
Requires-Dist: cw-rpa-unified-logger (==0.1.0rc10)
Requires-Dist: frozenlist (==1.5.0)
Requires-Dist: idna (==3.10)
Requires-Dist: multidict (==6.1.0)
Requires-Dist: propcache (==0.2.1)
Requires-Dist: requests (==2.32.3)
Requires-Dist: urllib3 (==2.3.0)
Requires-Dist: yarl (==1.18.3)
